ml_benchmark/__init__.py
ml_benchmark/benchmark_runner.py
ml_benchmark/config.py
ml_benchmark/decorators.py
ml_benchmark/latency_tracker.py
ml_benchmark/metrics.py
ml_benchmark/metrics_storage.py
ml_benchmark/resource_tracker.py
ml_benchmark/results_tracker.py
ml_benchmark/utils/__init__.py
ml_benchmark/utils/image_build_wrapper.py
ml_benchmark/utils/result_saver.py
ml_benchmark/utils/vanilla_grid_search.py
ml_benchmark/utils/yaml.py
ml_benchmark/workload/__init__.py
ml_benchmark/workload/objective.py
ml_benchmark/workload/mnist/__init__.py
ml_benchmark/workload/mnist/mlp.py
ml_benchmark/workload/mnist/mlp_objective.py
ml_benchmark/workload/mnist/mnist_task.py
ml_benchmark-0.4.2.dist-info/METADATA
ml_benchmark-0.4.2.dist-info/WHEEL
ml_benchmark-0.4.2.dist-info/top_level.txt
ml_benchmark-0.4.2.dist-info/RECORD
