Metadata-Version: 2.1
Name: ml-benchmark
Version: 0.4.2
Summary: ml_benchmark - A ML-Job for Benchmarking.
Home-page: https://github.com/gebauerm/ml_benchmark
Download-URL: https://github.com/gebauerm/ml_benchmark/archive/0.4.2.tar.gz
Author: Michael Gebauer, Sebastian Werner
Author-email: gebauerm23@gmail.com
License: MIT
Requires-Python: >=3.6
Requires-Dist: scikit-learn (==0.24.2)
Requires-Dist: tqdm (==4.62.3)
Requires-Dist: SQLAlchemy (==1.4.31)
Requires-Dist: docker (==4.4.2)
Requires-Dist: psycopg2-binary
Requires-Dist: prometheus-api-client (==0.5.1)
Requires-Dist: ruamel.yaml (==0.17.21)
Provides-Extra: test
Requires-Dist: pytest (==7.1.2) ; extra == 'test'
Requires-Dist: pytest-cov (==3.0.0) ; extra == 'test'
